README.md
setup.cfg
setup.py
email_verification/__init__.py
email_verification/client.py
email_verification/database.py
email_verification/service.py
email_verification.egg-info/PKG-INFO
email_verification.egg-info/SOURCES.txt
email_verification.egg-info/dependency_links.txt
email_verification.egg-info/requires.txt
email_verification.egg-info/top_level.txt
email_verification/api_client/__init__.py
email_verification/api_client/api_client.py
email_verification/api_handlers/BaseApiHandler.py
email_verification/api_handlers/EmailCountApiHandler.py
email_verification/api_handlers/EmailVerifierApiHandler.py
email_verification/api_handlers/__init__.py
email_verification/utils/__init__.py
email_verification/utils/response_normilizer.py