Metadata-Version: 2.1
Name: email_verification
Version: 0.4.6
Requires-Dist: requests>=2
Requires-Dist: urllib3==2.1.0
